cdk_immukv/__init__.py
cdk_immukv/py.typed
cdk_immukv/_jsii/__init__.py
cdk_immukv/_jsii/cdk-immukv@0.1.15.jsii.tgz
cdk_immukv-0.1.15.dist-info/LICENSE
cdk_immukv-0.1.15.dist-info/METADATA
cdk_immukv-0.1.15.dist-info/WHEEL
cdk_immukv-0.1.15.dist-info/top_level.txt
cdk_immukv-0.1.15.dist-info/RECORD
